cmdchess/__init__.py
cmdchess/board.py
cmdchess/config.py
cmdchess/game.py
cmdchess/piece.py
cmdchess/variant.py
cmdchess-0.1.3.dist-info/LICENSE
cmdchess-0.1.3.dist-info/METADATA
cmdchess-0.1.3.dist-info/WHEEL
cmdchess-0.1.3.dist-info/entry_points.txt
cmdchess-0.1.3.dist-info/top_level.txt
cmdchess-0.1.3.dist-info/RECORD
