Metadata-Version: 2.1
Name: cmdchess
Version: 0.1.3
Summary: A Windows command line application to play chess (specifically) using the command prompt.
Home-page: https://github.com/leonarduschen/cmdchess
Author: leonarduschen
Author-email: leonardus.chen@gmail.com
License: MIT
Platform: UNKNOWN
Requires-Dist: colorama (>=0.4.3)
